Flask_OAuthlib-0.9.3.dist-info/DESCRIPTION.rst
Flask_OAuthlib-0.9.3.dist-info/METADATA
Flask_OAuthlib-0.9.3.dist-info/RECORD
Flask_OAuthlib-0.9.3.dist-info/WHEEL
Flask_OAuthlib-0.9.3.dist-info/metadata.json
Flask_OAuthlib-0.9.3.dist-info/top_level.txt
flask_oauthlib/__init__.py
flask_oauthlib/client.py
flask_oauthlib/utils.py
flask_oauthlib/contrib/__init__.py
flask_oauthlib/contrib/apps.py
flask_oauthlib/contrib/cache.py
flask_oauthlib/contrib/oauth2.py
flask_oauthlib/contrib/client/__init__.py
flask_oauthlib/contrib/client/application.py
flask_oauthlib/contrib/client/descriptor.py
flask_oauthlib/contrib/client/exceptions.py
flask_oauthlib/contrib/client/signals.py
flask_oauthlib/contrib/client/structure.py
flask_oauthlib/provider/__init__.py
flask_oauthlib/provider/oauth1.py
flask_oauthlib/provider/oauth2.py
